gdecomp.cp38-win32.pyd
gdecomp-1.0.6.dist-info/LICENSE.txt
gdecomp-1.0.6.dist-info/METADATA
gdecomp-1.0.6.dist-info/WHEEL
gdecomp-1.0.6.dist-info/top_level.txt
gdecomp-1.0.6.dist-info/RECORD
