Metadata-Version: 2.1
Name: gdecomp
Version: 1.0.6
Summary: Gaussian Decompostion of a LiDAR Waveform
Home-page: https://gitlab.com/pytools4dart/gdecomp
Author: Florian de Boissieu
Author-email: fdeboiss@gmail.com
License: GPLv3
Platform: UNKNOWN
Classifier: Development Status :: 5 - Production/Stable
Classifier: Environment :: Console
Classifier: Intended Audience :: Developers
Classifier: Intended Audience :: Science/Research
Classifier: Topic :: Scientific/Engineering :: GIS
Classifier: Topic :: Scientific/Engineering :: Information Analysis
Classifier: License :: OSI Approved :: GNU General Public License v3 or later (GPLv3+)
Classifier: Programming Language :: Python :: 3
Classifier: Programming Language :: Python :: 3.7
Requires-Dist: numpy
Requires-Dist: cython
